common/__init__.py
common/decorators.py
common/descriptor.py
common/errors.py
common/metaclasses.py
common/utils.py
common/variables.py
project_logs/__init__.py
project_logs/configs/__init__.py
project_logs/configs/config_client_log.py
project_logs/configs/config_server_log.py
server/__init__.py
server/add_user.py
server/config_window.py
server/core.py
server/database.py
server/main_window.py
server/remove_user.py
server/statistics_window.py
unit_tests/__init__.py
mess_server_anna-0.0.1.dist-info/METADATA
mess_server_anna-0.0.1.dist-info/WHEEL
mess_server_anna-0.0.1.dist-info/top_level.txt
mess_server_anna-0.0.1.dist-info/RECORD
