Metadata-Version: 2.1
Name: mess-server-anna
Version: 0.0.1
Summary: mess_server_anna
Home-page: UNKNOWN
Author: Anna M.
Author-email: an.malch@gmail.com
License: UNKNOWN
Platform: UNKNOWN
Requires-Dist: PyQt5
Requires-Dist: sqlalchemy
Requires-Dist: pycryptodome
Requires-Dist: pycryptodomex
